[{"code":"2001","provinceCode":"91","regencyCode":"12","districtCode":"12","name":"Bape"},{"code":"2002","provinceCode":"91","regencyCode":"12","districtCode":"12","name":"Masim"},{"code":"2003","provinceCode":"91","regencyCode":"12","districtCode":"12","name":"Akmer"},{"code":"2004","provinceCode":"91","regencyCode":"12","districtCode":"12","name":"Kasawi"},{"code":"2005","provinceCode":"91","regencyCode":"12","districtCode":"12","name":"Tapasik Dua Bapenka"},{"code":"2006","provinceCode":"91","regencyCode":"12","districtCode":"12","name":"Ibot"}]