[{"id":"2001","provinceId":"52","regencyId":"04","districtId":"07","name":"Batu Rotok"},{"id":"2002","provinceId":"52","regencyId":"04","districtId":"07","name":"Tangkam Pulit"},{"id":"2003","provinceId":"52","regencyId":"04","districtId":"07","name":"Bao Desa"},{"id":"2004","provinceId":"52","regencyId":"04","districtId":"07","name":"Tepal"},{"id":"2005","provinceId":"52","regencyId":"04","districtId":"07","name":"Batu Dulang"},{"id":"2006","provinceId":"52","regencyId":"04","districtId":"07","name":"Kelungkung"}]