[{"code":"2001","provinceCode":"35","regencyCode":"24","districtCode":"21","name":"Geger"},{"code":"2002","provinceCode":"35","regencyCode":"24","districtCode":"21","name":"Badurame"},{"code":"2003","provinceCode":"35","regencyCode":"24","districtCode":"21","name":"Karangwedoro"},{"code":"2004","provinceCode":"35","regencyCode":"24","districtCode":"21","name":"Wangunrejo"},{"code":"2005","provinceCode":"35","regencyCode":"24","districtCode":"21","name":"Putatkumpul"},{"code":"2006","provinceCode":"35","regencyCode":"24","districtCode":"21","name":"Keben"},{"code":"2007","provinceCode":"35","regencyCode":"24","districtCode":"21","name":"Sukoanyar"},{"code":"2008","provinceCode":"35","regencyCode":"24","districtCode":"21","name":"Kemlagigede"},{"code":"2009","provinceCode":"35","regencyCode":"24","districtCode":"21","name":"Turi"},{"code":"2010","provinceCode":"35","regencyCode":"24","districtCode":"21","name":"Kemlagilor"},{"code":"2011","provinceCode":"35","regencyCode":"24","districtCode":"21","name":"Sukorejo"},{"code":"2012","provinceCode":"35","regencyCode":"24","districtCode":"21","name":"Tawangrejo"},{"code":"2013","provinceCode":"35","regencyCode":"24","districtCode":"21","name":"Bambang"},{"code":"2014","provinceCode":"35","regencyCode":"24","districtCode":"21","name":"Pomahanjanggan"},{"code":"2015","provinceCode":"35","regencyCode":"24","districtCode":"21","name":"Tambakploso"},{"code":"2016","provinceCode":"35","regencyCode":"24","districtCode":"21","name":"Balun"},{"code":"2017","provinceCode":"35","regencyCode":"24","districtCode":"21","name":"Ngujungrejo"},{"code":"2018","provinceCode":"35","regencyCode":"24","districtCode":"21","name":"Kepudibener"},{"code":"2019","provinceCode":"35","regencyCode":"24","districtCode":"21","name":"Gedungboyountung"}]