[{"id":"1003","provinceId":"62","regencyId":"10","districtId":"09","name":"Tumbang Napoi"},{"id":"2001","provinceId":"62","regencyId":"10","districtId":"09","name":"Tumbang Siruk"},{"id":"2002","provinceId":"62","regencyId":"10","districtId":"09","name":"Mangkuhung"},{"id":"2004","provinceId":"62","regencyId":"10","districtId":"09","name":"Tumbang Masukih"},{"id":"2005","provinceId":"62","regencyId":"10","districtId":"09","name":"Rangan Hiran"},{"id":"2006","provinceId":"62","regencyId":"10","districtId":"09","name":"Harowo"},{"id":"2007","provinceId":"62","regencyId":"10","districtId":"09","name":"Tumbang Manyoi"},{"id":"2008","provinceId":"62","regencyId":"10","districtId":"09","name":"Tumbang Lapan"},{"id":"2009","provinceId":"62","regencyId":"10","districtId":"09","name":"Buntoi"},{"id":"2010","provinceId":"62","regencyId":"10","districtId":"09","name":"Tumbang Koroi"},{"id":"2011","provinceId":"62","regencyId":"10","districtId":"09","name":"Tumbang Hatung"}]