[{"code":"2001","provinceCode":"91","regencyCode":"05","districtCode":"10","name":"Ambai I"},{"code":"2002","provinceCode":"91","regencyCode":"05","districtCode":"10","name":"Saweru"},{"code":"2004","provinceCode":"91","regencyCode":"05","districtCode":"10","name":"Kawipi"},{"code":"2005","provinceCode":"91","regencyCode":"05","districtCode":"10","name":"Wamori"},{"code":"2006","provinceCode":"91","regencyCode":"05","districtCode":"10","name":"Adiwipi"},{"code":"2007","provinceCode":"91","regencyCode":"05","districtCode":"10","name":"Umani"},{"code":"2008","provinceCode":"91","regencyCode":"05","districtCode":"10","name":"Ambai II"},{"code":"2009","provinceCode":"91","regencyCode":"05","districtCode":"10","name":"Mambawi"},{"code":"2010","provinceCode":"91","regencyCode":"05","districtCode":"10","name":"Baisore"},{"code":"2011","provinceCode":"91","regencyCode":"05","districtCode":"10","name":"Rondepi"},{"code":"2012","provinceCode":"91","regencyCode":"05","districtCode":"10","name":"Dorau"},{"code":"2013","provinceCode":"91","regencyCode":"05","districtCode":"10","name":"Perea"},{"code":"2014","provinceCode":"91","regencyCode":"05","districtCode":"10","name":"Imboriawa"},{"code":"2015","provinceCode":"91","regencyCode":"05","districtCode":"10","name":"Bairei"},{"code":"2016","provinceCode":"91","regencyCode":"05","districtCode":"10","name":"Aiwaraggani"},{"code":"2017","provinceCode":"91","regencyCode":"05","districtCode":"10","name":"Toroa"},{"code":"2018","provinceCode":"91","regencyCode":"05","districtCode":"10","name":"Nuniandei"},{"code":"2019","provinceCode":"91","regencyCode":"05","districtCode":"10","name":"Marawi"}]