[{"code":"2001","provinceCode":"62","regencyCode":"06","districtCode":"11","name":"Talingke"},{"code":"2002","provinceCode":"62","regencyCode":"06","districtCode":"11","name":"Hiyang Bana"},{"code":"2003","provinceCode":"62","regencyCode":"06","districtCode":"11","name":"Petak Bahandang"},{"code":"2004","provinceCode":"62","regencyCode":"06","districtCode":"11","name":"Handiwung"},{"code":"2005","provinceCode":"62","regencyCode":"06","districtCode":"11","name":"Tumbang Panggo"},{"code":"2006","provinceCode":"62","regencyCode":"06","districtCode":"11","name":"Tewang Tampang"},{"code":"2007","provinceCode":"62","regencyCode":"06","districtCode":"11","name":"Luwuk Kanan"},{"code":"2008","provinceCode":"62","regencyCode":"06","districtCode":"11","name":"Luwuk Kiri"}]