[{"code":"2001","provinceCode":"91","regencyCode":"28","districtCode":"02","name":"Damabagata"},{"code":"2002","provinceCode":"91","regencyCode":"28","districtCode":"02","name":"Kokobaya"},{"code":"2003","provinceCode":"91","regencyCode":"28","districtCode":"02","name":"Watiyai"},{"code":"2004","provinceCode":"91","regencyCode":"28","districtCode":"02","name":"Edagotadi"},{"code":"2005","provinceCode":"91","regencyCode":"28","districtCode":"02","name":"Dakebo"},{"code":"2006","provinceCode":"91","regencyCode":"28","districtCode":"02","name":"Bagou"},{"code":"2007","provinceCode":"91","regencyCode":"28","districtCode":"02","name":"Dagokebo"},{"code":"2008","provinceCode":"91","regencyCode":"28","districtCode":"02","name":"Ipoke"},{"code":"2009","provinceCode":"91","regencyCode":"28","districtCode":"02","name":"Waitakotu"},{"code":"2010","provinceCode":"91","regencyCode":"28","districtCode":"02","name":"Pekepa"},{"code":"2011","provinceCode":"91","regencyCode":"28","districtCode":"02","name":"Bagumoma"},{"code":"2012","provinceCode":"91","regencyCode":"28","districtCode":"02","name":"Udaugida"},{"code":"2013","provinceCode":"91","regencyCode":"28","districtCode":"02","name":"Bagou II"},{"code":"2014","provinceCode":"91","regencyCode":"28","districtCode":"02","name":"Idayodagi"}]