[{"code":"1001","provinceCode":"12","regencyCode":"19","districtCode":"01","name":"Pangkalan Dodek"},{"code":"1002","provinceCode":"12","regencyCode":"19","districtCode":"01","name":"Pangkalan Dodek Baru"},{"code":"1021","provinceCode":"12","regencyCode":"19","districtCode":"01","name":"Pagurawan"},{"code":"2003","provinceCode":"12","regencyCode":"19","districtCode":"01","name":"Aek Nauli"},{"code":"2004","provinceCode":"12","regencyCode":"19","districtCode":"01","name":"Durian"},{"code":"2005","provinceCode":"12","regencyCode":"19","districtCode":"01","name":"Lalang"},{"code":"2006","provinceCode":"12","regencyCode":"19","districtCode":"01","name":"Medang"},{"code":"2007","provinceCode":"12","regencyCode":"19","districtCode":"01","name":"Pakam"},{"code":"2008","provinceCode":"12","regencyCode":"19","districtCode":"01","name":"Pakam Raya"},{"code":"2009","provinceCode":"12","regencyCode":"19","districtCode":"01","name":"Pematang Cengkering"},{"code":"2010","provinceCode":"12","regencyCode":"19","districtCode":"01","name":"Sei Buah Keras"},{"code":"2011","provinceCode":"12","regencyCode":"19","districtCode":"01","name":"Sei Rakyat"},{"code":"2012","provinceCode":"12","regencyCode":"19","districtCode":"01","name":"Sidomulyo"},{"code":"2013","provinceCode":"12","regencyCode":"19","districtCode":"01","name":"Tanjung Sigoni"},{"code":"2014","provinceCode":"12","regencyCode":"19","districtCode":"01","name":"Nenas Siam"},{"code":"2015","provinceCode":"12","regencyCode":"19","districtCode":"01","name":"Pakam Raya Selatan"},{"code":"2016","provinceCode":"12","regencyCode":"19","districtCode":"01","name":"Mandarsah"},{"code":"2017","provinceCode":"12","regencyCode":"19","districtCode":"01","name":"Medang Baru"},{"code":"2018","provinceCode":"12","regencyCode":"19","districtCode":"01","name":"Pematang Nibung"},{"code":"2019","provinceCode":"12","regencyCode":"19","districtCode":"01","name":"Cengkering Pekan"},{"code":"2020","provinceCode":"12","regencyCode":"19","districtCode":"01","name":"Sei Raja"}]