[{"code":"1018","provinceCode":"17","regencyCode":"01","districtCode":"03","name":"Masat"},{"code":"2001","provinceCode":"17","regencyCode":"01","districtCode":"03","name":"Tanjung Aur I"},{"code":"2002","provinceCode":"17","regencyCode":"01","districtCode":"03","name":"Anggut"},{"code":"2003","provinceCode":"17","regencyCode":"01","districtCode":"03","name":"Tanjung Eran"},{"code":"2004","provinceCode":"17","regencyCode":"01","districtCode":"03","name":"Padang Lebar"},{"code":"2005","provinceCode":"17","regencyCode":"01","districtCode":"03","name":"Gedung Agung"},{"code":"2015","provinceCode":"17","regencyCode":"01","districtCode":"03","name":"Batu Bandung"},{"code":"2016","provinceCode":"17","regencyCode":"01","districtCode":"03","name":"Ulak Lebar"},{"code":"2017","provinceCode":"17","regencyCode":"01","districtCode":"03","name":"Kota Bumi"},{"code":"2019","provinceCode":"17","regencyCode":"01","districtCode":"03","name":"Air Umban"},{"code":"2020","provinceCode":"17","regencyCode":"01","districtCode":"03","name":"Sebilo"},{"code":"2021","provinceCode":"17","regencyCode":"01","districtCode":"03","name":"Ganjuh"},{"code":"2022","provinceCode":"17","regencyCode":"01","districtCode":"03","name":"Puding"},{"code":"2023","provinceCode":"17","regencyCode":"01","districtCode":"03","name":"Padang Tambak"},{"code":"2024","provinceCode":"17","regencyCode":"01","districtCode":"03","name":"Padang Mumpo"},{"code":"2025","provinceCode":"17","regencyCode":"01","districtCode":"03","name":"Beringin Datar"}]