[{"id":"2001","provinceId":"12","regencyId":"08","districtId":"26","name":"Cingkes"},{"id":"2002","provinceId":"12","regencyId":"08","districtId":"26","name":"Paribuan"},{"id":"2003","provinceId":"12","regencyId":"08","districtId":"26","name":"Saran Padang"},{"id":"2004","provinceId":"12","regencyId":"08","districtId":"26","name":"Mariah Dolok"},{"id":"2005","provinceId":"12","regencyId":"08","districtId":"26","name":"Marubun Lokkung"},{"id":"2006","provinceId":"12","regencyId":"08","districtId":"26","name":"Dolok Mariah"},{"id":"2007","provinceId":"12","regencyId":"08","districtId":"26","name":"Bawang"},{"id":"2008","provinceId":"12","regencyId":"08","districtId":"26","name":"Huta Saing"},{"id":"2009","provinceId":"12","regencyId":"08","districtId":"26","name":"Togur"},{"id":"2010","provinceId":"12","regencyId":"08","districtId":"26","name":"Perasmian"},{"id":"2011","provinceId":"12","regencyId":"08","districtId":"26","name":"Tanjung Purba"},{"id":"2012","provinceId":"12","regencyId":"08","districtId":"26","name":"Silau Marawan"},{"id":"2013","provinceId":"12","regencyId":"08","districtId":"26","name":"Bosi Sinumbah"},{"id":"2014","provinceId":"12","regencyId":"08","districtId":"26","name":"Ujung Bawang"}]