[{"code":"2001","provinceCode":"12","regencyCode":"24","districtCode":"01","name":"Hilidundra"},{"code":"2002","provinceCode":"12","regencyCode":"24","districtCode":"01","name":"Lawira Satua"},{"code":"2003","provinceCode":"12","regencyCode":"24","districtCode":"01","name":"Fadoro Fulolo"},{"code":"2004","provinceCode":"12","regencyCode":"24","districtCode":"01","name":"Lawira I"},{"code":"2005","provinceCode":"12","regencyCode":"24","districtCode":"01","name":"Hiligodu"},{"code":"2006","provinceCode":"12","regencyCode":"24","districtCode":"01","name":"Lombuza\\'ua"},{"code":"2007","provinceCode":"12","regencyCode":"24","districtCode":"01","name":"Maziaya"},{"code":"2008","provinceCode":"12","regencyCode":"24","districtCode":"01","name":"Baho"},{"code":"2009","provinceCode":"12","regencyCode":"24","districtCode":"01","name":"Lolofaoso"},{"code":"2010","provinceCode":"12","regencyCode":"24","districtCode":"01","name":"Lawira II"},{"code":"2011","provinceCode":"12","regencyCode":"24","districtCode":"01","name":"Dahadano"},{"code":"2012","provinceCode":"12","regencyCode":"24","districtCode":"01","name":"Lolomboli"},{"code":"2013","provinceCode":"12","regencyCode":"24","districtCode":"01","name":"Hiligeo Afia"}]