[{"code":"2001","provinceCode":"35","regencyCode":"03","districtCode":"06","name":"Kayen"},{"code":"2002","provinceCode":"35","regencyCode":"03","districtCode":"06","name":"Jati"},{"code":"2003","provinceCode":"35","regencyCode":"03","districtCode":"06","name":"Karangan"},{"code":"2004","provinceCode":"35","regencyCode":"03","districtCode":"06","name":"Kerjo"},{"code":"2005","provinceCode":"35","regencyCode":"03","districtCode":"06","name":"Kedungsigit"},{"code":"2006","provinceCode":"35","regencyCode":"03","districtCode":"06","name":"Salamrejo"},{"code":"2007","provinceCode":"35","regencyCode":"03","districtCode":"06","name":"Sukowetan"},{"code":"2008","provinceCode":"35","regencyCode":"03","districtCode":"06","name":"Ngentrong"},{"code":"2009","provinceCode":"35","regencyCode":"03","districtCode":"06","name":"Sumber"},{"code":"2010","provinceCode":"35","regencyCode":"03","districtCode":"06","name":"Buluagung"},{"code":"2011","provinceCode":"35","regencyCode":"03","districtCode":"06","name":"Sumberingin"},{"code":"2012","provinceCode":"35","regencyCode":"03","districtCode":"06","name":"Jatiprahu"}]